sigtonoise/__init__.py
sigtonoise/a.py
sigtonoise-1.0.1.dist-info/LICENSE.txt
sigtonoise-1.0.1.dist-info/METADATA
sigtonoise-1.0.1.dist-info/WHEEL
sigtonoise-1.0.1.dist-info/top_level.txt
sigtonoise-1.0.1.dist-info/RECORD
